intermarcheAPI/__init__.py
intermarcheAPI/post.py
intermarcheapi-0.0.1.dist-info/licenses/LICENSE
intermarcheapi-0.0.1.dist-info/METADATA
intermarcheapi-0.0.1.dist-info/WHEEL
intermarcheapi-0.0.1.dist-info/top_level.txt
intermarcheapi-0.0.1.dist-info/RECORD
