Metadata-Version: 2.4
Name: IntermarcheAPI
Version: 0.0.1
Summary: API d'intermarche simplement sur Python
Home-page: https://github.com/Zerbaib/IntermarcheAPI
Author: Hugo Hennetin
Author-email: hugo.hennetin@proton.me
Classifier: Programming Language :: Python :: 3
Classifier: License :: OSI Approved :: MIT License
Classifier: Operating System :: OS Independent
Requires-Python: >=3.11
License-File: LICENSE
Dynamic: author
Dynamic: author-email
Dynamic: classifier
Dynamic: description
Dynamic: description-content-type
Dynamic: home-page
Dynamic: license-file
Dynamic: requires-python
Dynamic: summary
